django_auth0_toolkit/__init__.py
django_auth0_toolkit/auth_api.py
django_auth0_toolkit/auth_backends.py
django_auth0_toolkit/django_auth.py
django_auth0_toolkit/exceptions.py
django_auth0_toolkit/middleware.py
django_auth0_toolkit/sso.py
django_auth0_toolkit/tokens.py
django_auth0_toolkit/views.py
django_auth0_toolkit-0.2.2.dist-info/DESCRIPTION.rst
django_auth0_toolkit-0.2.2.dist-info/METADATA
django_auth0_toolkit-0.2.2.dist-info/RECORD
django_auth0_toolkit-0.2.2.dist-info/WHEEL
django_auth0_toolkit-0.2.2.dist-info/metadata.json
django_auth0_toolkit-0.2.2.dist-info/top_level.txt
