Metadata-Version: 2.0
Name: django-auth0-toolkit
Version: 0.2.2
Summary: Toolkit for using Auth0 with Django projects
Home-page: https://github.com/shauns/django_auth0_toolkit
Author: Shaun Stanworth
Author-email: shaun.stanworth@googlemail.com
License: MIT license
Keywords: django_auth0_toolkit
Platform: UNKNOWN
Classifier: Development Status :: 2 - Pre-Alpha
Classifier: Intended Audience :: Developers
Classifier: License :: OSI Approved :: MIT License
Classifier: Natural Language :: English
Classifier: Programming Language :: Python :: 2
Classifier: Programming Language :: Python :: 2.6
Classifier: Programming Language :: Python :: 2.7
Classifier: Programming Language :: Python :: 3
Classifier: Programming Language :: Python :: 3.3
Classifier: Programming Language :: Python :: 3.4
Classifier: Programming Language :: Python :: 3.5
Requires-Dist: PyJWT (>=1.4.2)
Requires-Dist: requests (>=2)
